{
  "$schema": "https://vega.github.io/schema/vega-lite/v5.json",
  "title": {
    "text": "Top 15 Countries Globally with Surface Temperature Change (°C) and Top Countries By Region, in 2025",
    "subtitle": "Top 15 countries globally with the highest surface temperature changes are shown in the first filter, top countries in different regions shown in the region selection filters",
    "anchor": "start"
  },
  "width": 700,
  "height": 420,
  "data": {
    "url": "https://raw.githubusercontent.com/ninah134/FIT3179/main/Assignments/GlobalClimateData2025Updated.csv"
  },
  "params": [
    {
      "name": "Region_selection",
      "bind": {
        "input": "select",
        "options": [null, "Asia", "Europe", "Europe/Asia", "Middle East", "Oceania"],
        "labels": ["Show All", "Asia", "Europe", "Europe/Asia", "Middle East", "Oceania"],
        "name": "Region selection: "
      }
    }
  ],
  "transform": [
    {"calculate": "datum.temperature_anomaly_celsius", "as": "Temp_Anomaly"},
    {"calculate": "format(datum.Temp_Anomaly, '.2f') + '°C'", "as": "Temp_Label"},
    {
      "window": [{"op": "rank", "as": "GlobalRank"}],
      "sort": [{"field": "Temp_Anomaly", "order": "descending"}]
    },
    {"filter": "datum.GlobalRank <= 10"},
    {"filter": "Region_selection == null || datum.region == Region_selection"}
  ],
  "layer": [
    {
      "mark": {"type": "bar", "cornerRadiusEnd": 4},
      "encoding": {
        "y": {
          "field": "country",
          "type": "nominal",
          "sort": {"field": "Temp_Anomaly", "order": "descending"},
          "title": "Country Name"
        },
        "x": {
          "field": "Temp_Anomaly",
          "type": "quantitative",
          "title": "Amount of Average Surface Temperature Change (°C)"
        },
        "color": {
          "field": "region",
          "type": "nominal",
          "title": "Region",
          "scale": {
            "domain": ["Asia", "Europe", "Europe/Asia", "Middle East", "Oceania"],
            "range": ["#e41a1c", "#984ea3", "#ff7f00", "#a6cee3", "#377eb8"]
          }
        },
        "opacity": {"value": 0.6},
        "legend": {"title": "Region"},
        "tooltip": [
          {"field": "country", "title": "Country name:"},
          {"field": "region", "title": "Region:"},
          {"field": "Temp_Label", "title": "Temperature change:"}
        ]
      }
    },
    {
      "mark": {
        "type": "text",
        "align": "left",
        "baseline": "middle",
        "dx": -25,
        "fontSize": 11,
        "color": "white"
      },
      "encoding": {
        "y": {"field": "country", "type": "nominal", "sort": "-x"},
        "x": {"field": "Temp_Anomaly", "type": "quantitative"},
        "text": {"field": "Temp_Anomaly", "type": "quantitative", "format": ".2f"}
      }
    }
  ],
  "config": {
    "view": {"stroke": "transparent"},
    "axis": {"labelFontSize": 12, "titleFontSize": 13}
  }
}
